cdk_stacksets/__init__.py
cdk_stacksets/py.typed
cdk_stacksets/_jsii/__init__.py
cdk_stacksets/_jsii/cdk-stacksets@0.0.152.jsii.tgz
cdk_stacksets-0.0.152.dist-info/LICENSE
cdk_stacksets-0.0.152.dist-info/METADATA
cdk_stacksets-0.0.152.dist-info/WHEEL
cdk_stacksets-0.0.152.dist-info/top_level.txt
cdk_stacksets-0.0.152.dist-info/RECORD
